pynv/__init__.py
pynv/client.py
pynv/exceptions.py
pynv-0.3.dist-info/LICENSE
pynv-0.3.dist-info/METADATA
pynv-0.3.dist-info/WHEEL
pynv-0.3.dist-info/top_level.txt
pynv-0.3.dist-info/RECORD
