Metadata-Version: 2.1
Name: pynv
Version: 0.3
Summary: A Python library for interfacing with http://neurovault.org upload API
Home-page: https://github.com/neurolearn/pynv
Author: Anton Burnashev & Luke Chang
Author-email: luke.j.chang@dartmouth.edu
License: MIT
Keywords: neuroimaging,neurovault
Classifier: Programming Language :: Python
Classifier: Operating System :: OS Independent
Classifier: Intended Audience :: Science/Research
Classifier: License :: OSI Approved :: MIT License
License-File: LICENSE
Requires-Dist: requests >=2.10.0
